{
  "beslisboom": [
    {
      "voorwaarden": {
        "adl": "licht",
        "gedrag": "geen",
        "cognitie": "intact",
        "mantelzorg": "aanwezig"
      },
      "advies": "WLZ VV1",
      "onderbouwing": "Minimale zorg bij lichte beperkingen in geclusterde setting."
    },
    {
      "voorwaarden": {
        "adl": "matig",
        "gedrag": "rustig",
        "cognitie": "licht beperkt",
        "mantelzorg": "beperkt"
      },
      "advies": "WLZ VV2",
      "onderbouwing": "Toenemende behoefte aan ADL-ondersteuning met toezicht."
    },
    {
      "voorwaarden": {
        "adl": "matig",
        "gedrag": "vergeetachtig",
        "cognitie": "licht beperkt",
        "mantelzorg": "aanwezig"
      },
      "advies": "WLZ VV3",
      "onderbouwing": "Beginnende cognitieve problematiek met lichte gedragsveranderingen."
    },
    {
      "voorwaarden": {
        "adl": "matig",
        "gedrag": "vergeetachtig",
        "cognitie": "licht beperkt",
        "mantelzorg": "beperkt beschikbaar"
      },
      "advies": "WLZ VV4",
      "onderbouwing": "Toenemende ADL-beperkingen en lichte cognitieve achteruitgang."
    },
    {
      "voorwaarden": {
        "adl": "ernstig",
        "gedrag": "onvoorspelbaar",
        "cognitie": "verstoord",
        "mantelzorg": "afwezig"
      },
      "advies": "WLZ VV5",
      "onderbouwing": "Gedragsproblemen en verstoorde cognitie met structureel toezicht."
    },
    {
      "voorwaarden": {
        "adl": "ernstig",
        "gedrag": "verward",
        "cognitie": "matig beperkt",
        "mantelzorg": "afwezig"
      },
      "advies": "WLZ VV6",
      "onderbouwing": "Volledige overname van zorg noodzakelijk."
    },
    {
      "voorwaarden": {
        "adl": "ernstig",
        "gedrag": "desoriëntatie",
        "cognitie": "ernstig verstoord",
        "mantelzorg": "niet beschikbaar"
      },
      "advies": "WLZ VV7",
      "onderbouwing": "Gedragsproblematiek en volledige afhankelijkheid."
    },
    {
      "voorwaarden": {
        "adl": "zeer ernstig",
        "gedrag": "complex",
        "cognitie": "niet toetsbaar",
        "mantelzorg": "afwezig"
      },
      "advies": "WLZ VV8",
      "onderbouwing": "Zeer complexe zorg met 24-uurs toezicht."
    },
    {
      "voorwaarden": {
        "adl": "ernstig",
        "gedrag": "stabiel",
        "cognitie": "matig beperkt",
        "mantelzorg": "niet beschikbaar"
      },
      "advies": "WLZ VV9",
      "onderbouwing": "Intensieve begeleiding bij verstandelijke beperkingen."
    },
    {
      "voorwaarden": {
        "adl": "uitgebreid",
        "gedrag": "onvoorspelbaar",
        "cognitie": "sterk beperkt",
        "mantelzorg": "onvoldoende"
      },
      "advies": "WLZ VV10",
      "onderbouwing": "Maximale zorgzwaarte met gedragsregulatie en toezicht."
    },
    {
      "voorwaarden": {
        "adl": "beperkt",
        "gedrag": "ernstige psychiatrie",
        "cognitie": "verstoord",
        "mantelzorg": "niet beschikbaar"
      },
      "advies": "WLZ GGZ-B",
      "onderbouwing": "Beschermd wonen met langdurige psychiatrische ondersteuning."
    },
    {
      "voorwaarden": {
        "adl": "beperkt",
        "gedrag": "complex psychiatrisch",
        "cognitie": "ernstig verstoord",
        "mantelzorg": "afwezig"
      },
      "advies": "WLZ GGZ-C",
      "onderbouwing": "Langdurige klinische behandeling met intensieve begeleiding."
    },
    {
      "voorwaarden": {
        "adl": "licht",
        "gedrag": "geen",
        "cognitie": "licht beperkt",
        "mantelzorg": "beperkt"
      },
      "advies": "WLZ VG1",
      "onderbouwing": "Lichte verstandelijke beperking met beperkte toezichtbehoefte."
    },
    {
      "voorwaarden": {
        "adl": "matig",
        "gedrag": "ondersteuningsbehoefte",
        "cognitie": "vertraagd",
        "mantelzorg": "aanwezig"
      },
      "advies": "WLZ VG2",
      "onderbouwing": "Frequente ondersteuning in beschermde omgeving."
    },
    {
      "voorwaarden": {
        "adl": "matig",
        "gedrag": "afhankelijk",
        "cognitie": "vertraagd",
        "mantelzorg": "beperkt"
      },
      "advies": "WLZ VG3",
      "onderbouwing": "Beperkte zelfredzaamheid met behoefte aan gestructureerde zorg."
    },
    {
      "voorwaarden": {
        "adl": "beperkt",
        "gedrag": "rusteloos",
        "cognitie": "matig beperkt",
        "mantelzorg": "beperkt"
      },
      "advies": "WLZ VG4",
      "onderbouwing": "Dagstructuur nodig bij gedrags- en cognitieve problematiek."
    },
    {
      "voorwaarden": {
        "adl": "ernstig",
        "gedrag": "non-verbaal",
        "cognitie": "laag",
        "mantelzorg": "niet beschikbaar"
      },
      "advies": "WLZ VG5",
      "onderbouwing": "Volledige zorg en voortdurende begeleiding noodzakelijk."
    },
    {
      "voorwaarden": {
        "adl": "ernstig",
        "gedrag": "niet-prikkelbestendig",
        "cognitie": "beperkt",
        "mantelzorg": "niet beschikbaar"
      },
      "advies": "WLZ VG6",
      "onderbouwing": "Specifieke woonomgeving vereist bij complexe beperkingen."
    },
    {
      "voorwaarden": {
        "adl": "ernstig",
        "gedrag": "zelfverwondend",
        "cognitie": "laag",
        "mantelzorg": "afwezig"
      },
      "advies": "WLZ VG7",
      "onderbouwing": "1-op-1 begeleiding bij gedragsproblemen noodzakelijk."
    },
    {
      "voorwaarden": {
        "adl": "ernstig",
        "gedrag": "continu toezicht vereist",
        "cognitie": "onontwikkeld",
        "mantelzorg": "niet beschikbaar"
      },
      "advies": "WLZ VG8",
      "onderbouwing": "Maximale zorg bij ernstig verstandelijke beperking en gedragsproblematiek."
    },
    {
      "voorwaarden": {
        "adl": "ernstig",
        "gedrag": "beperkt",
        "cognitie": "laag",
        "mantelzorg": "niet beschikbaar"
      },
      "advies": "WLZ LG",
      "onderbouwing": "Blijvende lichamelijke beperking met intensieve lichamelijke zorg."
    },
    {
      "voorwaarden": {
        "adl": "ernstig",
        "gedrag": "auditief-visueel beperkt",
        "cognitie": "intact",
        "mantelzorg": "afwezig"
      },
      "advies": "WLZ ZG",
      "onderbouwing": "Specialistische ondersteuning bij zintuiglijke beperkingen."
    },
    {
      "voorwaarden": {
        "adl": "licht",
        "gedrag": "zelfstandig",
        "cognitie": "intact",
        "mantelzorg": "aanwezig"
      },
      "advies": "ZVW Wijkverpleging",
      "onderbouwing": "Thuiszorg voor persoonlijke verzorging/verpleging."
    },
    {
      "voorwaarden": {
        "adl": "matig",
        "gedrag": "vermoeid",
        "cognitie": "intact",
        "mantelzorg": "afwezig"
      },
      "advies": "ZVW Eerstelijnsverblijf",
      "onderbouwing": "Tijdelijke opname voor herstel of observatie."
    },
    {
      "voorwaarden": {
        "adl": "uitgebreid",
        "gedrag": "stabiel",
        "cognitie": "beperkt",
        "mantelzorg": "aanwezig"
      },
      "advies": "ZVW Palliatieve Terminale Zorg",
      "onderbouwing": "Zorg gericht op comfort in laatste levensfase."
    },
    {
      "voorwaarden": {
        "adl": "matig",
        "gedrag": "rustig",
        "cognitie": "intact",
        "mantelzorg": "beperkt"
      },
      "advies": "ZVW Verpleging bij chronische aandoening",
      "onderbouwing": "Langdurige verpleging bij bijvoorbeeld MS of Parkinson."
    },
    {
      "voorwaarden": {
        "adl": "licht",
        "gedrag": "sociaal beperkt",
        "cognitie": "intact",
        "mantelzorg": "aanwezig"
      },
      "advies": "WMO Begeleiding Individueel",
      "onderbouwing": "Ondersteuning bij zelfredzaamheid en structuur."
    },
    {
      "voorwaarden": {
        "adl": "licht",
        "gedrag": "teruggetrokken",
        "cognitie": "licht beperkt",
        "mantelzorg": "beperkt"
      },
      "advies": "WMO Begeleiding Groep",
      "onderbouwing": "Dagbesteding met activering in groepsverband."
    },
    {
      "voorwaarden": {
        "adl": "matig",
        "gedrag": "beperkt",
        "cognitie": "intact",
        "mantelzorg": "afwezig"
      },
      "advies": "WMO Huishoudelijke Ondersteuning",
      "onderbouwing": "Ondersteuning bij huishoudelijke taken."
    },
    {
      "voorwaarden": {
        "adl": "licht",
        "gedrag": "zorgbehoevend",
        "cognitie": "intact",
        "mantelzorg": "overbelast"
      },
      "advies": "WMO Respijtzorg",
      "onderbouwing": "Tijdelijke vervanging van mantelzorg."
    },
    {
      "voorwaarden": {
        "adl": "beperkt",
        "gedrag": "verward",
        "cognitie": "licht beperkt",
        "mantelzorg": "niet beschikbaar"
      },
      "advies": "WMO Beschermd Wonen",
      "onderbouwing": "Begeleid wonen bij psychische of sociale problemen."
    },
    {
      "voorwaarden": {
        "adl": "intact",
        "gedrag": "beperkt",
        "cognitie": "intact",
        "mantelzorg": "aanwezig"
      },
      "advies": "WMO Woonvoorzieningen",
      "onderbouwing": "Woningaanpassingen bij mobiliteitsproblemen."
    },
    {
      "voorwaarden": {
        "adl": "intact",
        "gedrag": "intact",
        "cognitie": "intact",
        "mantelzorg": "beperkt"
      },
      "advies": "WMO Vervoersvoorziening",
      "onderbouwing": "Vervoer voor mensen die geen gebruik kunnen maken van OV."
    }
  ]
}